<?xml version="1.0" encoding="UTF-8" standalone="yes"?>
<?xml-stylesheet href="hide-it.xsl" type="text/xsl"?>
<layoutype>fuckOFF</layoutype>
<fanart>https://offshoregit.com/c0ldfire/zip/plugin.video.no-name/fanart.jpg</fanart>
<SetViewMode>1</SetViewMode>
<items>
<item>
	<title>[COLOR=white]Batman XXX: A Porn Parody[/COLOR]</title>
	<meta>
	<imdb>tt1653823</imdb>
	<content>movie</content>
	<title>Batman XXX: A Porn Parody</title>
	<year>2010</year>
	</meta>
	<link>
	<sublink name=[COLOR lime]Torrent Link[/COLOR]>plugin://plugin.video.elementum/movie/39531/links/</sublink>
	<sublink name=[COLOR lime]Torrent Search Link[/COLOR]>plugin://plugin.video.elementum/search?q=Batman%20XXX:%20A%20Porn%20Parody</sublink>
	</link>
	<thumbnail>https://image.tmdb.org/t/p/w1280/mKCcmo48O3WN4egveW9hmOWtv86.jpg</thumbnail>
	<fanart>https://image.tmdb.org/t/p/w1280</fanart>
</item>
<item>
	<title>[COLOR=white]Superman XXX: A Porn Parody[/COLOR]</title>
	<meta>
	<imdb>tt1818417</imdb>
	<content>movie</content>
	<title>Superman XXX: A Porn Parody</title>
	<year>2011</year>
	</meta>
	<link>
	<sublink name=[COLOR lime]Torrent Link[/COLOR]>plugin://plugin.video.elementum/movie/58715/links/</sublink>
	<sublink name=[COLOR lime]Torrent Search Link[/COLOR]>plugin://plugin.video.elementum/search?q=Superman%20XXX:%20A%20Porn%20Parody</sublink>
	</link>
	<thumbnail>https://image.tmdb.org/t/p/w1280/oKmwNrVBbhfccL6KHbtea4QX9qB.jpg</thumbnail>
	<fanart>https://image.tmdb.org/t/p/w1280</fanart>
</item>
<item>
	<title>[COLOR=white]Spider-Man XXX: A Porn Parody[/COLOR]</title>
	<meta>
	<imdb>tt2056702</imdb>
	<content>movie</content>
	<title>Spider-Man XXX: A Porn Parody</title>
	<year>2011</year>
	</meta>
	<link>
	<sublink name=[COLOR lime]Torrent Link[/COLOR]>plugin://plugin.video.elementum/movie/86738/links/</sublink>
	<sublink name=[COLOR lime]Torrent Search Link[/COLOR]>plugin://plugin.video.elementum/search?q=Spider-Man%20XXX:%20A%20Porn%20Parody</sublink>
	</link>
	<thumbnail>https://image.tmdb.org/t/p/w1280/59GnglqRhdptsed8MmVv2sinC3K.jpg</thumbnail>
	<fanart>https://image.tmdb.org/t/p/w1280/5FpET8beEwOugBHE62c9vZ3Uokh.jpg</fanart>
</item>
<item>
	<title>[COLOR=white]Malice in LaLaLand[/COLOR]</title>
	<meta>
	<imdb>tt1482454</imdb>
	<content>movie</content>
	<title>Malice in LaLaLand</title>
	<year>2010</year>
	</meta>
	<link>
	<sublink name=[COLOR lime]Torrent Link[/COLOR]>plugin://plugin.video.elementum/movie/68036/links/</sublink>
	<sublink name=[COLOR lime]Torrent Search Link[/COLOR]>plugin://plugin.video.elementum/search?q=Malice%20in%20LaLaLand</sublink>
	</link>
	<thumbnail>https://image.tmdb.org/t/p/w1280/ck2DbSp023JCrjPdgYKmy33Ml99.jpg</thumbnail>
	<fanart>https://image.tmdb.org/t/p/w1280</fanart>
</item>
<item>
	<title>[COLOR=white]American Dad XXX Parody[/COLOR]</title>
	<meta>
	<imdb></imdb>
	<content>movie</content>
	<title>American Dad XXX Parody</title>
	<year>2011</year>
	</meta>
	<link>
	<sublink name=[COLOR lime]Torrent Link[/COLOR]>plugin://plugin.video.elementum/movie/113476/links/</sublink>
	<sublink name=[COLOR lime]Torrent Search Link[/COLOR]>plugin://plugin.video.elementum/search?q=American%20Dad%20XXX%20Parody</sublink>
	</link>
	<thumbnail>https://image.tmdb.org/t/p/w1280/iuzrTpC7I4SofQkXyqksQiCI6L4.jpg</thumbnail>
	<fanart>https://image.tmdb.org/t/p/w1280</fanart>
</item>
<item>
	<title>[COLOR=white]Red Riding Hood XXX: A Triple X Parody[/COLOR]</title>
	<meta>
	<imdb>tt2708500</imdb>
	<content>movie</content>
	<title>Red Riding Hood XXX: A Triple X Parody</title>
	<year>2010</year>
	</meta>
	<link>
	<sublink name=[COLOR lime]Torrent Link[/COLOR]>plugin://plugin.video.elementum/movie/95272/links/</sublink>
	<sublink name=[COLOR lime]Torrent Search Link[/COLOR]>plugin://plugin.video.elementum/search?q=Red%20Riding%20Hood%20XXX:%20A%20Triple%20X%20Parody</sublink>
	</link>
	<thumbnail>https://image.tmdb.org/t/p/w1280/vlTv8stOFpU0wunA9mBYE0ERleP.jpg</thumbnail>
	<fanart>https://image.tmdb.org/t/p/w1280</fanart>
</item>
<item>
	<title>[COLOR=white]Big Bang Theory: A XXX Parody[/COLOR]</title>
	<meta>
	<imdb>tt1627031</imdb>
	<content>movie</content>
	<title>Big Bang Theory: A XXX Parody</title>
	<year>2010</year>
	</meta>
	<link>
	<sublink name=[COLOR lime]Torrent Link[/COLOR]>plugin://plugin.video.elementum/movie/36905/links/</sublink>
	<sublink name=[COLOR lime]Torrent Search Link[/COLOR]>plugin://plugin.video.elementum/search?q=Big%20Bang%20Theory:%20A%20XXX%20Parody</sublink>
	</link>
	<thumbnail>https://image.tmdb.org/t/p/w1280/h37F26q2dPUYv7szwgGTQ9LZ8CY.jpg</thumbnail>
	<fanart>https://image.tmdb.org/t/p/w1280</fanart>
</item>
<item>
	<title>[COLOR=white]Star Wars XXX: A Porn Parody[/COLOR]</title>
	<meta>
	<imdb>tt2059288</imdb>
	<content>movie</content>
	<title>Star Wars XXX: A Porn Parody</title>
	<year>2012</year>
	</meta>
	<link>
	<sublink name=[COLOR red]trailer Link[/COLOR]>https://www.youtube.com/watch?v=X56oTgum_VQ&feature=youtu.be (Play Trailer)</sublink>
	<sublink name=[COLOR lime]Torrent Link[/COLOR]>plugin://plugin.video.elementum/movie/96697/links/</sublink>
	<sublink name=[COLOR lime]Torrent Search Link[/COLOR]>plugin://plugin.video.elementum/search?q=Star%20Wars%20XXX:%20A%20Porn%20Parody</sublink>
	</link>
	<thumbnail>https://image.tmdb.org/t/p/w1280/5Rs8hHb3ouXR45r80P2rsdSnD63.jpg</thumbnail>
	<fanart>https://image.tmdb.org/t/p/w1280</fanart>
</item>
<item>
	<title>[COLOR=white]30 Rock: A XXX Parody[/COLOR]</title>
	<meta>
	<imdb>tt1499909</imdb>
	<content>movie</content>
	<title>30 Rock: A XXX Parody</title>
	<year>2009</year>
	</meta>
	<link>
	<sublink name=[COLOR red]trailer Link[/COLOR]>https://www.youtube.com/watch?v=X56oTgum_VQ&feature=youtu.be (Play Trailer)</sublink>
	<sublink name=[COLOR lime]Torrent Link[/COLOR]>plugin://plugin.video.elementum/movie/45152/links/</sublink>
	<sublink name=[COLOR lime]Torrent Search Link[/COLOR]>plugin://plugin.video.elementum/search?q=30%20Rock:%20A%20XXX%20Parody</sublink>
	</link>
	<thumbnail>https://image.tmdb.org/t/p/w1280/lxALfjf2aQThB7Y4Wr9WDI5eQFS.jpg</thumbnail>
	<fanart>https://image.tmdb.org/t/p/w1280</fanart>
</item>
<item>
	<title>[COLOR=white]Friends: A XXX Parody[/COLOR]</title>
	<meta>
	<imdb>tt1481360</imdb>
	<content>movie</content>
	<title>Friends: A XXX Parody</title>
	<year>2009</year>
	</meta>
	<link>
	<sublink name=[COLOR red]trailer Link[/COLOR]>https://www.youtube.com/watch?v=X56oTgum_VQ&feature=youtu.be (Play Trailer)</sublink>
	<sublink name=[COLOR lime]Torrent Link[/COLOR]>plugin://plugin.video.elementum/movie/41375/links/</sublink>
	<sublink name=[COLOR lime]Torrent Search Link[/COLOR]>plugin://plugin.video.elementum/search?q=Friends:%20A%20XXX%20Parody</sublink>
	</link>
	<thumbnail>https://image.tmdb.org/t/p/w1280/jQ5rZcAcxgUvvajot2z3NYegnYE.jpg</thumbnail>
	<fanart>https://image.tmdb.org/t/p/w1280/jGSpEvt9XKtzOsO5uyvTBtZfuU5.jpg</fanart>
</item>
<item>
	<title>[COLOR=white]Scrubs: A XXX Parody[/COLOR]</title>
	<meta>
	<imdb>tt1621929</imdb>
	<content>movie</content>
	<title>Scrubs: A XXX Parody</title>
	<year>2009</year>
	</meta>
	<link>
	<sublink name=[COLOR red]trailer Link[/COLOR]>https://www.youtube.com/watch?v=X56oTgum_VQ&feature=youtu.be (Play Trailer)</sublink>
	<sublink name=[COLOR lime]Torrent Link[/COLOR]>plugin://plugin.video.elementum/movie/26284/links/</sublink>
	<sublink name=[COLOR lime]Torrent Search Link[/COLOR]>plugin://plugin.video.elementum/search?q=Scrubs:%20A%20XXX%20Parody</sublink>
	</link>
	<thumbnail>https://image.tmdb.org/t/p/w1280/qpnXsIhhOqFdr3fpaTeoXzeOkuC.jpg</thumbnail>
	<fanart>https://image.tmdb.org/t/p/w1280</fanart>
</item>
<item>
	<title>[COLOR=white]Avengers XXX: A Porn Parody[/COLOR]</title>
	<meta>
	<imdb>tt2332811</imdb>
	<content>movie</content>
	<title>Avengers XXX: A Porn Parody</title>
	<year>2012</year>
	</meta>
	<link>
	<sublink name=[COLOR red]trailer Link[/COLOR]>https://www.youtube.com/watch?v=X56oTgum_VQ&feature=youtu.be (Play Trailer)</sublink>
	<sublink name=[COLOR lime]Torrent Link[/COLOR]>plugin://plugin.video.elementum/movie/135636/links/</sublink>
	<sublink name=[COLOR lime]Torrent Search Link[/COLOR]>plugin://plugin.video.elementum/search?q=Avengers%20XXX:%20A%20Porn%20Parody</sublink>
	</link>
	<thumbnail>https://image.tmdb.org/t/p/w1280/3wGG7ShIAqXhSebujKG6i1W2cv1.jpg</thumbnail>
	<fanart>https://image.tmdb.org/t/p/w1280</fanart>
</item>
<item>
	<title>[COLOR=white]The A-Team XXX: A Parody[/COLOR]</title>
	<meta>
	<imdb>tt1693967</imdb>
	<content>movie</content>
	<title>The A-Team XXX: A Parody</title>
	<year>2010</year>
	</meta>
	<link>
	<sublink name=[COLOR red]trailer Link[/COLOR]>https://www.youtube.com/watch?v=mKqlW9-wxRE&feature=youtu.be (Play Trailer)</sublink>
	<sublink name=[COLOR lime]Torrent Link[/COLOR]>plugin://plugin.video.elementum/movie/143194/links/</sublink>
	<sublink name=[COLOR lime]Torrent Search Link[/COLOR]>plugin://plugin.video.elementum/search?q=The%20A-Team%20XXX:%20A%20Parody</sublink>
	</link>
	<thumbnail>https://image.tmdb.org/t/p/w1280/7EIf5fxXOtGO1o596dDcNBgPBv1.jpg</thumbnail>
	<fanart>https://image.tmdb.org/t/p/w1280</fanart>
</item>
<item>
	<title>[COLOR=white]Scream XXX: A Porn Parody[/COLOR]</title>
	<meta>
	<imdb>tt2015481</imdb>
	<content>movie</content>
	<title>Scream XXX: A Porn Parody</title>
	<year>2011</year>
	</meta>
	<link>
	<sublink name=[COLOR red]trailer Link[/COLOR]>https://www.youtube.com/watch?v=mKqlW9-wxRE&feature=youtu.be (Play Trailer)</sublink>
	<sublink name=[COLOR lime]Torrent Link[/COLOR]>plugin://plugin.video.elementum/movie/62809/links/</sublink>
	<sublink name=[COLOR lime]Torrent Search Link[/COLOR]>plugin://plugin.video.elementum/search?q=Scream%20XXX:%20A%20Porn%20Parody</sublink>
	</link>
	<thumbnail>https://image.tmdb.org/t/p/w1280/sHA1hHQTFEtI5nX6ixXbfJkFYIq.jpg</thumbnail>
	<fanart>https://image.tmdb.org/t/p/w1280</fanart>
</item>
<item>
	<title>[COLOR=white]Bring It On: A XXX Porn Parody[/COLOR]</title>
	<meta>
	<imdb>tt2083941</imdb>
	<content>movie</content>
	<title>Bring It On: A XXX Porn Parody</title>
	<year>2011</year>
	</meta>
	<link>
	<sublink name=[COLOR red]trailer Link[/COLOR]>https://www.youtube.com/watch?v=mKqlW9-wxRE&feature=youtu.be (Play Trailer)</sublink>
	<sublink name=[COLOR lime]Torrent Link[/COLOR]>plugin://plugin.video.elementum/movie/73149/links/</sublink>
	<sublink name=[COLOR lime]Torrent Search Link[/COLOR]>plugin://plugin.video.elementum/search?q=Bring%20It%20On:%20A%20XXX%20Porn%20Parody</sublink>
	</link>
	<thumbnail>https://image.tmdb.org/t/p/w1280/zsvBjd1muXP8YcwVktHHTNr1WBl.jpg</thumbnail>
	<fanart>https://image.tmdb.org/t/p/w1280</fanart>
</item>



</items>
